aibo/__init__.py
aibo/chat.py
aibo/config.py
aibo/main.py
aibo/record.py
aibo/text_to_speech.py
aibo/transcribe.py
tests/__init__.py
aibo-0.0.4.dist-info/LICENSE
aibo-0.0.4.dist-info/METADATA
aibo-0.0.4.dist-info/WHEEL
aibo-0.0.4.dist-info/entry_points.txt
aibo-0.0.4.dist-info/top_level.txt
aibo-0.0.4.dist-info/RECORD
