Metadata-Version: 2.1
Name: aibo
Version: 0.0.4
Summary: aibo: AI partner that can run offline
Home-page: https://github.com/JUO-Inc/aibo
Author: Aibo Community
Author-email: koki.noda.contact@gmail.com
License: MIT
Keywords: LLM language model offline NLP speech deep learning transformer pytorch tensorflow GPT smart speaker
Requires-Python: >=3.7.0
License-File: LICENSE
Requires-Dist: click
Requires-Dist: pyttsx3
Requires-Dist: pyaudio
Requires-Dist: openai-whisper
